{
	"id": "0da40f81-64dd-4566-8e4b-b22c2badbaaf",
	"subtopic": "99509FA3DC4F4159B557",
	"timeStamp": "2023-09-22T08:52:07.626Z",
	"topic": "concur.fgi.obligation",
	"eventType": "ObligationAcknowledgement",
	"facts": {
		"userId": "d11e2b64-603f-4541-b7d1-7cf66300a939",
		"syncTime": null,
		"entityId": "p10021624iza",
		"id": null,
		"docId": "99509FA3DC4F4159B557",
		"docTypeId": "REPORT",
		"refId": "e4196ea4-109a-4548-9640-1578b99269d0",
		"eventData": "{\"code\":0,\"docId\":\"e4196ea4109a454896401578b99269d0\",\"systemId\":\"QVMCLNT600\",\"acknowledgeResult\":\"SUCCESS\",\"errorMessage\":\"\"}",
		"errorData": "",
		"error": false,
		"companyId": "7094240a-5c94-48ba-b69b-84c9dff4ef50"
	},
	"correlationId": "cfa020a0-aabf-4b87-a321-9385b9ba8737"
}
